setup.py
beautystyle/code.py
beautystyle.egg-info/PKG-INFO
beautystyle.egg-info/SOURCES.txt
beautystyle.egg-info/dependency_links.txt
beautystyle.egg-info/top_level.txt