Metadata-Version: 2.1
Name: beautystyle
Version: 1.0
Summary: color manager.
Author: helper
License: MIT
Keywords: style
Classifier: Development Status :: 5 - Production/Stable
